README.md
setup.cfg
setup.py
pymadoka/__init__.py
pymadoka/cli.py
pymadoka/connection.py
pymadoka/consts.py
pymadoka/controller.py
pymadoka/feature.py
pymadoka/mqtt.py
pymadoka/transport.py
pymadoka.egg-info/PKG-INFO
pymadoka.egg-info/SOURCES.txt
pymadoka.egg-info/dependency_links.txt
pymadoka.egg-info/entry_points.txt
pymadoka.egg-info/requires.txt
pymadoka.egg-info/top_level.txt
pymadoka/features/__init__.py
pymadoka/features/clean_filter.py
pymadoka/features/fanspeed.py
pymadoka/features/operationmode.py
pymadoka/features/power.py
pymadoka/features/setpoint.py
pymadoka/features/temperatures.py