Metadata-Version: 1.0
Name: pymadoka
Version: 0.2.5
Summary: A library to control Daikin BRC1H (Madoka) thermostats
Home-page: https://github.com/mduran80/pymadoka
Author: Manuel Durán
Author-email: manuelduran@gmail.com
License: MIT
Keywords: thermostat homeautomation bluetooth
Platform: UNKNOWN
